scrapy_jsonrpc-0.3.0.dist-info/RECORD
scrapy_jsonrpc-0.3.0.dist-info/WHEEL
scrapy_jsonrpc-0.3.0.dist-info/metadata.json
scrapy_jsonrpc-0.3.0.dist-info/DESCRIPTION.rst
scrapy_jsonrpc-0.3.0.dist-info/METADATA
scrapy_jsonrpc-0.3.0.dist-info/top_level.txt
scrapy_jsonrpc/webservice.py
scrapy_jsonrpc/txweb.py
scrapy_jsonrpc/serialize.py
scrapy_jsonrpc/jsonrpc.py
scrapy_jsonrpc/__init__.py
