Metadata-Version: 2.0
Name: scrapy-jsonrpc
Version: 0.3.0
Summary: Scrapy extenstion to control spiders using JSON-RPC
Home-page: https://github.com/scrapy/scrapy-jsonrpc
Author: Scrapy developers
Author-email: UNKNOWN
License: BSD
Platform: UNKNOWN
Classifier: Framework :: Scrapy
Classifier: Development Status :: 4 - Beta
Classifier: Environment :: Console
Classifier: Intended Audience :: Developers
Classifier: License :: OSI Approved :: BSD License
Classifier: Operating System :: OS Independent
Classifier: Programming Language :: Python
Classifier: Programming Language :: Python :: 2
Classifier: Programming Language :: Python :: 2.7
Classifier: Topic :: Internet :: WWW/HTTP
Requires-Dist: Twisted (>=10.0.0)
Requires-Dist: Scrapy (>=0.24.0)
Requires-Dist: six (>=1.5.2)
